{
  "generated_at": "2026-05-05T16:58:35.048182+00:00",
  "quality_gate_threshold": 0.35,
  "snapshot_counts": {
    "fundamentals": 20,
    "news": 20,
    "insiders": 20
  },
  "counts": {
    "INVEST_PAPER": 5,
    "MONITOR": 7,
    "QUALITY_REJECT": 6,
    "PASS": 2
  },
  "top": [
    {
      "symbol": "VRT",
      "sit_score": 0.9,
      "decision": "INVEST_PAPER",
      "committee_score": 0.4088,
      "confidence": 81.9,
      "risk_state": "NORMAL",
      "target_weight": 0.0527,
      "votes": [
        {
          "agent": "Warren Buffett value",
          "verdict": "HOLD",
          "confidence": 75.7,
          "score": 0.37,
          "rationale": "expensive PE; debt acceptable; positive free cash flow; ROE quality; profitable margins",
          "data_scope": [
            "fundamentals"
          ]
        },
        {
          "agent": "Charlie Munger fundamental+news",
          "verdict": "BUY",
          "confidence": 98.2,
          "score": 0.46,
          "rationale": "revenue growth; earnings growth; gross margin quality; news tone positive",
          "data_scope": [
            "fundamentals",
            "news"
          ]
        },
        {
          "agent": "Bill Ackman fundamental+insider",
          "verdict": "MONITOR",
          "confidence": 61.8,
          "score": 0.14,
          "rationale": "cashflow + growth",
          "data_scope": [
            "fundamentals",
            "insider"
          ]
        },
        {
          "agent": "Steve Cohen technical",
          "verdict": "BUY",
          "confidence": 99.0,
          "score": 0.6,
          "rationale": "bullish EMA stack; 20d momentum positive",
          "data_scope": [
            "price",
            "volume",
            "ma",
            "rsi"
          ]
        },
        {
          "agent": "Ray Dalio macro/price",
          "verdict": "HOLD",
          "confidence": 75.0,
          "score": 0.35,
          "rationale": "benchmark supportive; medium-term relative momentum",
          "data_scope": [
            "price",
            "benchmark",
            "volatility"
          ]
        }
      ],
      "rationale": "confidence-weighted score 0.41; risk=NORMAL; active_agents=5/5"
    },
    {
      "symbol": "FSLR",
      "sit_score": 0.56,
      "decision": "INVEST_PAPER",
      "committee_score": 0.3925,
      "confidence": 74.0,
      "risk_state": "NORMAL",
      "target_weight": 0.0514,
      "votes": [
        {
          "agent": "Warren Buffett value",
          "verdict": "BUY",
          "confidence": 100,
          "score": 0.7,
          "rationale": "reasonable PE; debt acceptable; positive free cash flow; ROE quality; profitable margins",
          "data_scope": [
            "fundamentals"
          ]
        },
        {
          "agent": "Charlie Munger fundamental+news",
          "verdict": "BUY",
          "confidence": 100,
          "score": 0.51,
          "rationale": "revenue growth; earnings growth; gross margin quality; news tone positive",
          "data_scope": [
            "fundamentals",
            "news"
          ]
        },
        {
          "agent": "Bill Ackman fundamental+insider",
          "verdict": "MONITOR",
          "confidence": 47.4,
          "score": -0.02,
          "rationale": "cashflow + growth; insider activity skews sell",
          "data_scope": [
            "fundamentals",
            "insider"
          ]
        },
        {
          "agent": "Steve Cohen technical",
          "verdict": "HOLD",
          "confidence": 67.5,
          "score": 0.25,
          "rationale": "20d momentum positive",
          "data_scope": [
            "price",
            "volume",
            "ma",
            "rsi"
          ]
        },
        {
          "agent": "Ray Dalio macro/price",
          "verdict": "HOLD",
          "confidence": 55.0,
          "score": 0.15,
          "rationale": "benchmark supportive",
          "data_scope": [
            "price",
            "benchmark",
            "volatility"
          ]
        }
      ],
      "rationale": "confidence-weighted score 0.39; risk=NORMAL; active_agents=5/5"
    },
    {
      "symbol": "AAPL",
      "sit_score": 0.72,
      "decision": "INVEST_PAPER",
      "committee_score": 0.3886,
      "confidence": 76.8,
      "risk_state": "NORMAL",
      "target_weight": 0.0511,
      "votes": [
        {
          "agent": "Warren Buffett value",
          "verdict": "BUY",
          "confidence": 92.2,
          "score": 0.52,
          "rationale": "debt acceptable; positive free cash flow; ROE quality; profitable margins",
          "data_scope": [
            "fundamentals"
          ]
        },
        {
          "agent": "Charlie Munger fundamental+news",
          "verdict": "HOLD",
          "confidence": 92.2,
          "score": 0.41,
          "rationale": "revenue growth; earnings growth; gross margin quality; news tone positive",
          "data_scope": [
            "fundamentals",
            "news"
          ]
        },
        {
          "agent": "Bill Ackman fundamental+insider",
          "verdict": "MONITOR",
          "confidence": 47.4,
          "score": -0.02,
          "rationale": "cashflow + growth; insider activity skews sell",
          "data_scope": [
            "fundamentals",
            "insider"
          ]
        },
        {
          "agent": "Steve Cohen technical",
          "verdict": "BUY",
          "confidence": 97.0,
          "score": 0.5782,
          "rationale": "bullish EMA stack; 20d momentum positive",
          "data_scope": [
            "price",
            "volume",
            "ma",
            "rsi"
          ]
        },
        {
          "agent": "Ray Dalio macro/price",
          "verdict": "HOLD",
          "confidence": 55.0,
          "score": 0.15,
          "rationale": "benchmark supportive",
          "data_scope": [
            "price",
            "benchmark",
            "volatility"
          ]
        }
      ],
      "rationale": "confidence-weighted score 0.39; risk=NORMAL; active_agents=5/5"
    },
    {
      "symbol": "AME",
      "sit_score": 0.72,
      "decision": "INVEST_PAPER",
      "committee_score": 0.3729,
      "confidence": 77.5,
      "risk_state": "NORMAL",
      "target_weight": 0.0498,
      "votes": [
        {
          "agent": "Warren Buffett value",
          "verdict": "BUY",
          "confidence": 92.2,
          "score": 0.52,
          "rationale": "debt acceptable; positive free cash flow; ROE quality; profitable margins",
          "data_scope": [
            "fundamentals"
          ]
        },
        {
          "agent": "Charlie Munger fundamental+news",
          "verdict": "HOLD",
          "confidence": 86.2,
          "score": 0.36,
          "rationale": "revenue growth; earnings growth; gross margin quality",
          "data_scope": [
            "fundamentals",
            "news"
          ]
        },
        {
          "agent": "Bill Ackman fundamental+insider",
          "verdict": "MONITOR",
          "confidence": 61.8,
          "score": 0.14,
          "rationale": "cashflow + growth",
          "data_scope": [
            "fundamentals",
            "insider"
          ]
        },
        {
          "agent": "Steve Cohen technical",
          "verdict": "BUY",
          "confidence": 92.4,
          "score": 0.5266,
          "rationale": "bullish EMA stack; 20d momentum positive",
          "data_scope": [
            "price",
            "volume",
            "ma",
            "rsi"
          ]
        },
        {
          "agent": "Ray Dalio macro/price",
          "verdict": "HOLD",
          "confidence": 55.0,
          "score": 0.15,
          "rationale": "benchmark supportive",
          "data_scope": [
            "price",
            "benchmark",
            "volatility"
          ]
        }
      ],
      "rationale": "confidence-weighted score 0.37; risk=NORMAL; active_agents=5/5"
    },
    {
      "symbol": "MSFT",
      "sit_score": 0.42,
      "decision": "INVEST_PAPER",
      "committee_score": 0.3692,
      "confidence": 74.4,
      "risk_state": "NORMAL",
      "target_weight": 0.0495,
      "votes": [
        {
          "agent": "Warren Buffett value",
          "verdict": "BUY",
          "confidence": 100,
          "score": 0.7,
          "rationale": "reasonable PE; debt acceptable; positive free cash flow; ROE quality; profitable margins",
          "data_scope": [
            "fundamentals"
          ]
        },
        {
          "agent": "Charlie Munger fundamental+news",
          "verdict": "HOLD",
          "confidence": 92.2,
          "score": 0.41,
          "rationale": "revenue growth; earnings growth; gross margin quality; news tone positive",
          "data_scope": [
            "fundamentals",
            "news"
          ]
        },
        {
          "agent": "Bill Ackman fundamental+insider",
          "verdict": "MONITOR",
          "confidence": 61.8,
          "score": 0.14,
          "rationale": "cashflow + growth",
          "data_scope": [
            "fundamentals",
            "insider"
          ]
        },
        {
          "agent": "Steve Cohen technical",
          "verdict": "HOLD",
          "confidence": 63.1,
          "score": 0.2007,
          "rationale": "20d momentum positive",
          "data_scope": [
            "price",
            "volume",
            "ma",
            "rsi"
          ]
        },
        {
          "agent": "Ray Dalio macro/price",
          "verdict": "HOLD",
          "confidence": 55.0,
          "score": 0.15,
          "rationale": "benchmark supportive",
          "data_scope": [
            "price",
            "benchmark",
            "volatility"
          ]
        }
      ],
      "rationale": "confidence-weighted score 0.37; risk=NORMAL; active_agents=5/5"
    },
    {
      "symbol": "SMCI",
      "sit_score": 0.42,
      "decision": "MONITOR",
      "committee_score": 0.3369,
      "confidence": 74.1,
      "risk_state": "NORMAL",
      "target_weight": 0.0,
      "votes": [
        {
          "agent": "Warren Buffett value",
          "verdict": "BUY",
          "confidence": 100,
          "score": 0.6,
          "rationale": "reasonable PE; debt acceptable; positive free cash flow; ROE quality",
          "data_scope": [
            "fundamentals"
          ]
        },
        {
          "agent": "Charlie Munger fundamental+news",
          "verdict": "HOLD",
          "confidence": 86.2,
          "score": 0.36,
          "rationale": "revenue growth; earnings growth; news tone positive",
          "data_scope": [
            "fundamentals",
            "news"
          ]
        },
        {
          "agent": "Bill Ackman fundamental+insider",
          "verdict": "MONITOR",
          "confidence": 61.8,
          "score": 0.14,
          "rationale": "cashflow + growth",
          "data_scope": [
            "fundamentals",
            "insider"
          ]
        },
        {
          "agent": "Steve Cohen technical",
          "verdict": "HOLD",
          "confidence": 67.5,
          "score": 0.25,
          "rationale": "20d momentum positive",
          "data_scope": [
            "price",
            "volume",
            "ma",
            "rsi"
          ]
        },
        {
          "agent": "Ray Dalio macro/price",
          "verdict": "HOLD",
          "confidence": 55.0,
          "score": 0.15,
          "rationale": "benchmark supportive",
          "data_scope": [
            "price",
            "benchmark",
            "volatility"
          ]
        }
      ],
      "rationale": "confidence-weighted score 0.34; risk=NORMAL; active_agents=5/5"
    },
    {
      "symbol": "NVDA",
      "sit_score": 0.56,
      "decision": "MONITOR",
      "committee_score": 0.2908,
      "confidence": 69.1,
      "risk_state": "NORMAL",
      "target_weight": 0.0,
      "votes": [
        {
          "agent": "Warren Buffett value",
          "verdict": "BUY",
          "confidence": 92.2,
          "score": 0.52,
          "rationale": "debt acceptable; positive free cash flow; ROE quality; profitable margins",
          "data_scope": [
            "fundamentals"
          ]
        },
        {
          "agent": "Charlie Munger fundamental+news",
          "verdict": "HOLD",
          "confidence": 86.2,
          "score": 0.36,
          "rationale": "revenue growth; earnings growth; gross margin quality",
          "data_scope": [
            "fundamentals",
            "news"
          ]
        },
        {
          "agent": "Bill Ackman fundamental+insider",
          "verdict": "MONITOR",
          "confidence": 47.4,
          "score": -0.02,
          "rationale": "cashflow + growth; insider activity skews sell",
          "data_scope": [
            "fundamentals",
            "insider"
          ]
        },
        {
          "agent": "Steve Cohen technical",
          "verdict": "HOLD",
          "confidence": 64.8,
          "score": 0.2197,
          "rationale": "20d momentum positive",
          "data_scope": [
            "price",
            "volume",
            "ma",
            "rsi"
          ]
        },
        {
          "agent": "Ray Dalio macro/price",
          "verdict": "HOLD",
          "confidence": 55.0,
          "score": 0.15,
          "rationale": "benchmark supportive",
          "data_scope": [
            "price",
            "benchmark",
            "volatility"
          ]
        }
      ],
      "rationale": "confidence-weighted score 0.29; risk=NORMAL; active_agents=5/5"
    },
    {
      "symbol": "IONQ",
      "sit_score": 0.9,
      "decision": "MONITOR",
      "committee_score": 0.2747,
      "confidence": 71.6,
      "risk_state": "NORMAL",
      "target_weight": 0.0,
      "votes": [
        {
          "agent": "Warren Buffett value",
          "verdict": "MONITOR",
          "confidence": 48.2,
          "score": 0.12,
          "rationale": "debt acceptable",
          "data_scope": [
            "fundamentals"
          ]
        },
        {
          "agent": "Charlie Munger fundamental+news",
          "verdict": "HOLD",
          "confidence": 71.8,
          "score": 0.24,
          "rationale": "revenue growth; gross margin quality",
          "data_scope": [
            "fundamentals",
            "news"
          ]
        },
        {
          "agent": "Bill Ackman fundamental+insider",
          "verdict": "MONITOR",
          "confidence": 64.2,
          "score": -0.16,
          "rationale": "insider activity skews sell",
          "data_scope": [
            "fundamentals",
            "insider"
          ]
        },
        {
          "agent": "Steve Cohen technical",
          "verdict": "BUY",
          "confidence": 99.0,
          "score": 0.6,
          "rationale": "bullish EMA stack; 20d momentum positive",
          "data_scope": [
            "price",
            "volume",
            "ma",
            "rsi"
          ]
        },
        {
          "agent": "Ray Dalio macro/price",
          "verdict": "HOLD",
          "confidence": 75.0,
          "score": 0.35,
          "rationale": "benchmark supportive; medium-term relative momentum",
          "data_scope": [
            "price",
            "benchmark",
            "volatility"
          ]
        }
      ],
      "rationale": "confidence-weighted score 0.27; risk=NORMAL; active_agents=5/5"
    },
    {
      "symbol": "NKE",
      "sit_score": 0.0,
      "decision": "QUALITY_REJECT",
      "committee_score": 0.255,
      "confidence": 0.0,
      "risk_state": "N/A",
      "target_weight": 0.0,
      "votes": [
        {
          "agent": "Warren Buffett value",
          "verdict": "BUY",
          "confidence": 100,
          "score": 0.6,
          "rationale": "reasonable PE; debt acceptable; positive free cash flow; ROE quality",
          "data_scope": [
            "fundamentals"
          ]
        },
        {
          "agent": "Charlie Munger fundamental+news",
          "verdict": "MONITOR",
          "confidence": 49.0,
          "score": 0.05,
          "rationale": "gross margin quality; news tone negative",
          "data_scope": [
            "fundamentals",
            "news"
          ]
        },
        {
          "agent": "Bill Ackman fundamental+insider",
          "verdict": "HOLD",
          "confidence": 81.0,
          "score": 0.3,
          "rationale": "cashflow + growth; insider activity skews buy",
          "data_scope": [
            "fundamentals",
            "insider"
          ]
        },
        {
          "agent": "Steve Cohen technical",
          "verdict": "MONITOR",
          "confidence": 57.2,
          "score": -0.135,
          "rationale": "20d momentum positive; weak RSI",
          "data_scope": [
            "price",
            "volume",
            "ma",
            "rsi"
          ]
        },
        {
          "agent": "Ray Dalio macro/price",
          "verdict": "HOLD",
          "confidence": 55.0,
          "score": 0.15,
          "rationale": "benchmark supportive",
          "data_scope": [
            "price",
            "benchmark",
            "volatility"
          ]
        }
      ],
      "rationale": "SIT 0.00 below gate 0.35"
    },
    {
      "symbol": "CCJ",
      "sit_score": 0.56,
      "decision": "MONITOR",
      "committee_score": 0.2373,
      "confidence": 66.6,
      "risk_state": "NORMAL",
      "target_weight": 0.0,
      "votes": [
        {
          "agent": "Warren Buffett value",
          "verdict": "HOLD",
          "confidence": 62.5,
          "score": 0.25,
          "rationale": "expensive PE; debt acceptable; positive free cash flow; profitable margins",
          "data_scope": [
            "fundamentals"
          ]
        },
        {
          "agent": "Charlie Munger fundamental+news",
          "verdict": "HOLD",
          "confidence": 81.4,
          "score": 0.32,
          "rationale": "earnings growth; gross margin quality; news tone positive",
          "data_scope": [
            "fundamentals",
            "news"
          ]
        },
        {
          "agent": "Bill Ackman fundamental+insider",
          "verdict": "HOLD",
          "confidence": 81.0,
          "score": 0.3,
          "rationale": "cashflow + growth; insider activity skews buy",
          "data_scope": [
            "fundamentals",
            "insider"
          ]
        },
        {
          "agent": "Steve Cohen technical",
          "verdict": "MONITOR",
          "confidence": 53.1,
          "score": 0.0904,
          "rationale": "20d momentum positive",
          "data_scope": [
            "price",
            "volume",
            "ma",
            "rsi"
          ]
        },
        {
          "agent": "Ray Dalio macro/price",
          "verdict": "HOLD",
          "confidence": 55.0,
          "score": 0.15,
          "rationale": "benchmark supportive",
          "data_scope": [
            "price",
            "benchmark",
            "volatility"
          ]
        }
      ],
      "rationale": "confidence-weighted score 0.24; risk=NORMAL; active_agents=5/5"
    },
    {
      "symbol": "QUBT",
      "sit_score": 0.72,
      "decision": "MONITOR",
      "committee_score": 0.2193,
      "confidence": 65.2,
      "risk_state": "NORMAL",
      "target_weight": 0.0,
      "votes": [
        {
          "agent": "Warren Buffett value",
          "verdict": "MONITOR",
          "confidence": 48.2,
          "score": 0.12,
          "rationale": "debt acceptable",
          "data_scope": [
            "fundamentals"
          ]
        },
        {
          "agent": "Charlie Munger fundamental+news",
          "verdict": "MONITOR",
          "confidence": 59.8,
          "score": 0.14,
          "rationale": "revenue growth",
          "data_scope": [
            "fundamentals",
            "news"
          ]
        },
        {
          "agent": "Bill Ackman fundamental+insider",
          "verdict": "MONITOR",
          "confidence": 64.2,
          "score": -0.16,
          "rationale": "insider activity skews sell",
          "data_scope": [
            "fundamentals",
            "insider"
          ]
        },
        {
          "agent": "Steve Cohen technical",
          "verdict": "BUY",
          "confidence": 99.0,
          "score": 0.6,
          "rationale": "bullish EMA stack; 20d momentum positive",
          "data_scope": [
            "price",
            "volume",
            "ma",
            "rsi"
          ]
        },
        {
          "agent": "Ray Dalio macro/price",
          "verdict": "HOLD",
          "confidence": 55.0,
          "score": 0.15,
          "rationale": "benchmark supportive",
          "data_scope": [
            "price",
            "benchmark",
            "volatility"
          ]
        }
      ],
      "rationale": "confidence-weighted score 0.22; risk=NORMAL; active_agents=5/5"
    },
    {
      "symbol": "PLTR",
      "sit_score": 0.18,
      "decision": "QUALITY_REJECT",
      "committee_score": 0.2145,
      "confidence": 0.0,
      "risk_state": "N/A",
      "target_weight": 0.0,
      "votes": [
        {
          "agent": "Warren Buffett value",
          "verdict": "HOLD",
          "confidence": 75.7,
          "score": 0.37,
          "rationale": "expensive PE; debt acceptable; positive free cash flow; ROE quality; profitable margins",
          "data_scope": [
            "fundamentals"
          ]
        },
        {
          "agent": "Charlie Munger fundamental+news",
          "verdict": "HOLD",
          "confidence": 86.2,
          "score": 0.36,
          "rationale": "revenue growth; earnings growth; gross margin quality",
          "data_scope": [
            "fundamentals",
            "news"
          ]
        },
        {
          "agent": "Bill Ackman fundamental+insider",
          "verdict": "MONITOR",
          "confidence": 47.4,
          "score": -0.02,
          "rationale": "cashflow + growth; insider activity skews sell",
          "data_scope": [
            "fundamentals",
            "insider"
          ]
        },
        {
          "agent": "Steve Cohen technical",
          "verdict": "MONITOR",
          "confidence": 45.0,
          "score": 0.0,
          "rationale": "mixed technicals",
          "data_scope": [
            "price",
            "volume",
            "ma",
            "rsi"
          ]
        },
        {
          "agent": "Ray Dalio macro/price",
          "verdict": "HOLD",
          "confidence": 55.0,
          "score": 0.15,
          "rationale": "benchmark supportive",
          "data_scope": [
            "price",
            "benchmark",
            "volatility"
          ]
        }
      ],
      "rationale": "SIT 0.18 below gate 0.35"
    }
  ],
  "agent_heatmap": [
    {
      "symbol": "VRT",
      "decision": "INVEST_PAPER",
      "target_weight": 0.0527,
      "committee_score": 0.4088,
      "votes": [
        {
          "agent": "Warren Buffett value",
          "verdict": "HOLD",
          "confidence": 75.7,
          "score": 0.37,
          "rationale": "expensive PE; debt acceptable; positive free cash flow; ROE quality; profitable margins"
        },
        {
          "agent": "Charlie Munger fundamental+news",
          "verdict": "BUY",
          "confidence": 98.2,
          "score": 0.46,
          "rationale": "revenue growth; earnings growth; gross margin quality; news tone positive"
        },
        {
          "agent": "Bill Ackman fundamental+insider",
          "verdict": "MONITOR",
          "confidence": 61.8,
          "score": 0.14,
          "rationale": "cashflow + growth"
        },
        {
          "agent": "Steve Cohen technical",
          "verdict": "BUY",
          "confidence": 99.0,
          "score": 0.6,
          "rationale": "bullish EMA stack; 20d momentum positive"
        },
        {
          "agent": "Ray Dalio macro/price",
          "verdict": "HOLD",
          "confidence": 75.0,
          "score": 0.35,
          "rationale": "benchmark supportive; medium-term relative momentum"
        }
      ]
    },
    {
      "symbol": "FSLR",
      "decision": "INVEST_PAPER",
      "target_weight": 0.0514,
      "committee_score": 0.3925,
      "votes": [
        {
          "agent": "Warren Buffett value",
          "verdict": "BUY",
          "confidence": 100,
          "score": 0.7,
          "rationale": "reasonable PE; debt acceptable; positive free cash flow; ROE quality; profitable margins"
        },
        {
          "agent": "Charlie Munger fundamental+news",
          "verdict": "BUY",
          "confidence": 100,
          "score": 0.51,
          "rationale": "revenue growth; earnings growth; gross margin quality; news tone positive"
        },
        {
          "agent": "Bill Ackman fundamental+insider",
          "verdict": "MONITOR",
          "confidence": 47.4,
          "score": -0.02,
          "rationale": "cashflow + growth; insider activity skews sell"
        },
        {
          "agent": "Steve Cohen technical",
          "verdict": "HOLD",
          "confidence": 67.5,
          "score": 0.25,
          "rationale": "20d momentum positive"
        },
        {
          "agent": "Ray Dalio macro/price",
          "verdict": "HOLD",
          "confidence": 55.0,
          "score": 0.15,
          "rationale": "benchmark supportive"
        }
      ]
    },
    {
      "symbol": "AAPL",
      "decision": "INVEST_PAPER",
      "target_weight": 0.0511,
      "committee_score": 0.3886,
      "votes": [
        {
          "agent": "Warren Buffett value",
          "verdict": "BUY",
          "confidence": 92.2,
          "score": 0.52,
          "rationale": "debt acceptable; positive free cash flow; ROE quality; profitable margins"
        },
        {
          "agent": "Charlie Munger fundamental+news",
          "verdict": "HOLD",
          "confidence": 92.2,
          "score": 0.41,
          "rationale": "revenue growth; earnings growth; gross margin quality; news tone positive"
        },
        {
          "agent": "Bill Ackman fundamental+insider",
          "verdict": "MONITOR",
          "confidence": 47.4,
          "score": -0.02,
          "rationale": "cashflow + growth; insider activity skews sell"
        },
        {
          "agent": "Steve Cohen technical",
          "verdict": "BUY",
          "confidence": 97.0,
          "score": 0.5782,
          "rationale": "bullish EMA stack; 20d momentum positive"
        },
        {
          "agent": "Ray Dalio macro/price",
          "verdict": "HOLD",
          "confidence": 55.0,
          "score": 0.15,
          "rationale": "benchmark supportive"
        }
      ]
    },
    {
      "symbol": "AME",
      "decision": "INVEST_PAPER",
      "target_weight": 0.0498,
      "committee_score": 0.3729,
      "votes": [
        {
          "agent": "Warren Buffett value",
          "verdict": "BUY",
          "confidence": 92.2,
          "score": 0.52,
          "rationale": "debt acceptable; positive free cash flow; ROE quality; profitable margins"
        },
        {
          "agent": "Charlie Munger fundamental+news",
          "verdict": "HOLD",
          "confidence": 86.2,
          "score": 0.36,
          "rationale": "revenue growth; earnings growth; gross margin quality"
        },
        {
          "agent": "Bill Ackman fundamental+insider",
          "verdict": "MONITOR",
          "confidence": 61.8,
          "score": 0.14,
          "rationale": "cashflow + growth"
        },
        {
          "agent": "Steve Cohen technical",
          "verdict": "BUY",
          "confidence": 92.4,
          "score": 0.5266,
          "rationale": "bullish EMA stack; 20d momentum positive"
        },
        {
          "agent": "Ray Dalio macro/price",
          "verdict": "HOLD",
          "confidence": 55.0,
          "score": 0.15,
          "rationale": "benchmark supportive"
        }
      ]
    },
    {
      "symbol": "MSFT",
      "decision": "INVEST_PAPER",
      "target_weight": 0.0495,
      "committee_score": 0.3692,
      "votes": [
        {
          "agent": "Warren Buffett value",
          "verdict": "BUY",
          "confidence": 100,
          "score": 0.7,
          "rationale": "reasonable PE; debt acceptable; positive free cash flow; ROE quality; profitable margins"
        },
        {
          "agent": "Charlie Munger fundamental+news",
          "verdict": "HOLD",
          "confidence": 92.2,
          "score": 0.41,
          "rationale": "revenue growth; earnings growth; gross margin quality; news tone positive"
        },
        {
          "agent": "Bill Ackman fundamental+insider",
          "verdict": "MONITOR",
          "confidence": 61.8,
          "score": 0.14,
          "rationale": "cashflow + growth"
        },
        {
          "agent": "Steve Cohen technical",
          "verdict": "HOLD",
          "confidence": 63.1,
          "score": 0.2007,
          "rationale": "20d momentum positive"
        },
        {
          "agent": "Ray Dalio macro/price",
          "verdict": "HOLD",
          "confidence": 55.0,
          "score": 0.15,
          "rationale": "benchmark supportive"
        }
      ]
    },
    {
      "symbol": "SMCI",
      "decision": "MONITOR",
      "target_weight": 0.0,
      "committee_score": 0.3369,
      "votes": [
        {
          "agent": "Warren Buffett value",
          "verdict": "BUY",
          "confidence": 100,
          "score": 0.6,
          "rationale": "reasonable PE; debt acceptable; positive free cash flow; ROE quality"
        },
        {
          "agent": "Charlie Munger fundamental+news",
          "verdict": "HOLD",
          "confidence": 86.2,
          "score": 0.36,
          "rationale": "revenue growth; earnings growth; news tone positive"
        },
        {
          "agent": "Bill Ackman fundamental+insider",
          "verdict": "MONITOR",
          "confidence": 61.8,
          "score": 0.14,
          "rationale": "cashflow + growth"
        },
        {
          "agent": "Steve Cohen technical",
          "verdict": "HOLD",
          "confidence": 67.5,
          "score": 0.25,
          "rationale": "20d momentum positive"
        },
        {
          "agent": "Ray Dalio macro/price",
          "verdict": "HOLD",
          "confidence": 55.0,
          "score": 0.15,
          "rationale": "benchmark supportive"
        }
      ]
    },
    {
      "symbol": "NVDA",
      "decision": "MONITOR",
      "target_weight": 0.0,
      "committee_score": 0.2908,
      "votes": [
        {
          "agent": "Warren Buffett value",
          "verdict": "BUY",
          "confidence": 92.2,
          "score": 0.52,
          "rationale": "debt acceptable; positive free cash flow; ROE quality; profitable margins"
        },
        {
          "agent": "Charlie Munger fundamental+news",
          "verdict": "HOLD",
          "confidence": 86.2,
          "score": 0.36,
          "rationale": "revenue growth; earnings growth; gross margin quality"
        },
        {
          "agent": "Bill Ackman fundamental+insider",
          "verdict": "MONITOR",
          "confidence": 47.4,
          "score": -0.02,
          "rationale": "cashflow + growth; insider activity skews sell"
        },
        {
          "agent": "Steve Cohen technical",
          "verdict": "HOLD",
          "confidence": 64.8,
          "score": 0.2197,
          "rationale": "20d momentum positive"
        },
        {
          "agent": "Ray Dalio macro/price",
          "verdict": "HOLD",
          "confidence": 55.0,
          "score": 0.15,
          "rationale": "benchmark supportive"
        }
      ]
    },
    {
      "symbol": "IONQ",
      "decision": "MONITOR",
      "target_weight": 0.0,
      "committee_score": 0.2747,
      "votes": [
        {
          "agent": "Warren Buffett value",
          "verdict": "MONITOR",
          "confidence": 48.2,
          "score": 0.12,
          "rationale": "debt acceptable"
        },
        {
          "agent": "Charlie Munger fundamental+news",
          "verdict": "HOLD",
          "confidence": 71.8,
          "score": 0.24,
          "rationale": "revenue growth; gross margin quality"
        },
        {
          "agent": "Bill Ackman fundamental+insider",
          "verdict": "MONITOR",
          "confidence": 64.2,
          "score": -0.16,
          "rationale": "insider activity skews sell"
        },
        {
          "agent": "Steve Cohen technical",
          "verdict": "BUY",
          "confidence": 99.0,
          "score": 0.6,
          "rationale": "bullish EMA stack; 20d momentum positive"
        },
        {
          "agent": "Ray Dalio macro/price",
          "verdict": "HOLD",
          "confidence": 75.0,
          "score": 0.35,
          "rationale": "benchmark supportive; medium-term relative momentum"
        }
      ]
    },
    {
      "symbol": "NKE",
      "decision": "QUALITY_REJECT",
      "target_weight": 0.0,
      "committee_score": 0.255,
      "votes": [
        {
          "agent": "Warren Buffett value",
          "verdict": "BUY",
          "confidence": 100,
          "score": 0.6,
          "rationale": "reasonable PE; debt acceptable; positive free cash flow; ROE quality"
        },
        {
          "agent": "Charlie Munger fundamental+news",
          "verdict": "MONITOR",
          "confidence": 49.0,
          "score": 0.05,
          "rationale": "gross margin quality; news tone negative"
        },
        {
          "agent": "Bill Ackman fundamental+insider",
          "verdict": "HOLD",
          "confidence": 81.0,
          "score": 0.3,
          "rationale": "cashflow + growth; insider activity skews buy"
        },
        {
          "agent": "Steve Cohen technical",
          "verdict": "MONITOR",
          "confidence": 57.2,
          "score": -0.135,
          "rationale": "20d momentum positive; weak RSI"
        },
        {
          "agent": "Ray Dalio macro/price",
          "verdict": "HOLD",
          "confidence": 55.0,
          "score": 0.15,
          "rationale": "benchmark supportive"
        }
      ]
    },
    {
      "symbol": "CCJ",
      "decision": "MONITOR",
      "target_weight": 0.0,
      "committee_score": 0.2373,
      "votes": [
        {
          "agent": "Warren Buffett value",
          "verdict": "HOLD",
          "confidence": 62.5,
          "score": 0.25,
          "rationale": "expensive PE; debt acceptable; positive free cash flow; profitable margins"
        },
        {
          "agent": "Charlie Munger fundamental+news",
          "verdict": "HOLD",
          "confidence": 81.4,
          "score": 0.32,
          "rationale": "earnings growth; gross margin quality; news tone positive"
        },
        {
          "agent": "Bill Ackman fundamental+insider",
          "verdict": "HOLD",
          "confidence": 81.0,
          "score": 0.3,
          "rationale": "cashflow + growth; insider activity skews buy"
        },
        {
          "agent": "Steve Cohen technical",
          "verdict": "MONITOR",
          "confidence": 53.1,
          "score": 0.0904,
          "rationale": "20d momentum positive"
        },
        {
          "agent": "Ray Dalio macro/price",
          "verdict": "HOLD",
          "confidence": 55.0,
          "score": 0.15,
          "rationale": "benchmark supportive"
        }
      ]
    },
    {
      "symbol": "QUBT",
      "decision": "MONITOR",
      "target_weight": 0.0,
      "committee_score": 0.2193,
      "votes": [
        {
          "agent": "Warren Buffett value",
          "verdict": "MONITOR",
          "confidence": 48.2,
          "score": 0.12,
          "rationale": "debt acceptable"
        },
        {
          "agent": "Charlie Munger fundamental+news",
          "verdict": "MONITOR",
          "confidence": 59.8,
          "score": 0.14,
          "rationale": "revenue growth"
        },
        {
          "agent": "Bill Ackman fundamental+insider",
          "verdict": "MONITOR",
          "confidence": 64.2,
          "score": -0.16,
          "rationale": "insider activity skews sell"
        },
        {
          "agent": "Steve Cohen technical",
          "verdict": "BUY",
          "confidence": 99.0,
          "score": 0.6,
          "rationale": "bullish EMA stack; 20d momentum positive"
        },
        {
          "agent": "Ray Dalio macro/price",
          "verdict": "HOLD",
          "confidence": 55.0,
          "score": 0.15,
          "rationale": "benchmark supportive"
        }
      ]
    },
    {
      "symbol": "PLTR",
      "decision": "QUALITY_REJECT",
      "target_weight": 0.0,
      "committee_score": 0.2145,
      "votes": [
        {
          "agent": "Warren Buffett value",
          "verdict": "HOLD",
          "confidence": 75.7,
          "score": 0.37,
          "rationale": "expensive PE; debt acceptable; positive free cash flow; ROE quality; profitable margins"
        },
        {
          "agent": "Charlie Munger fundamental+news",
          "verdict": "HOLD",
          "confidence": 86.2,
          "score": 0.36,
          "rationale": "revenue growth; earnings growth; gross margin quality"
        },
        {
          "agent": "Bill Ackman fundamental+insider",
          "verdict": "MONITOR",
          "confidence": 47.4,
          "score": -0.02,
          "rationale": "cashflow + growth; insider activity skews sell"
        },
        {
          "agent": "Steve Cohen technical",
          "verdict": "MONITOR",
          "confidence": 45.0,
          "score": 0.0,
          "rationale": "mixed technicals"
        },
        {
          "agent": "Ray Dalio macro/price",
          "verdict": "HOLD",
          "confidence": 55.0,
          "score": 0.15,
          "rationale": "benchmark supportive"
        }
      ]
    },
    {
      "symbol": "KULR",
      "decision": "MONITOR",
      "target_weight": 0.0,
      "committee_score": 0.1398,
      "votes": [
        {
          "agent": "Warren Buffett value",
          "verdict": "MONITOR",
          "confidence": 48.2,
          "score": 0.12,
          "rationale": "debt acceptable"
        },
        {
          "agent": "Charlie Munger fundamental+news",
          "verdict": "MONITOR",
          "confidence": 55.0,
          "score": 0.1,
          "rationale": "news tone positive"
        },
        {
          "agent": "Bill Ackman fundamental+insider",
          "verdict": "HOLD",
          "confidence": 64.2,
          "score": 0.16,
          "rationale": "insider activity skews buy"
        },
        {
          "agent": "Steve Cohen technical",
          "verdict": "HOLD",
          "confidence": 67.5,
          "score": 0.25,
          "rationale": "20d momentum positive"
        },
        {
          "agent": "Ray Dalio macro/price",
          "verdict": "MONITOR",
          "confidence": 40.0,
          "score": 0.0,
          "rationale": "benchmark supportive; high volatility haircut"
        }
      ]
    },
    {
      "symbol": "VST",
      "decision": "MONITOR",
      "target_weight": 0.0,
      "committee_score": 0.1391,
      "votes": [
        {
          "agent": "Warren Buffett value",
          "verdict": "MONITOR",
          "confidence": 37.2,
          "score": -0.02,
          "rationale": "high leverage; ROE quality"
        },
        {
          "agent": "Charlie Munger fundamental+news",
          "verdict": "HOLD",
          "confidence": 71.8,
          "score": 0.24,
          "rationale": "revenue growth; gross margin quality"
        },
        {
          "agent": "Bill Ackman fundamental+insider",
          "verdict": "MONITOR",
          "confidence": 59.4,
          "score": -0.12,
          "rationale": "balance sheet activism risk"
        },
        {
          "agent": "Steve Cohen technical",
          "verdict": "MONITOR",
          "confidence": 54.7,
          "score": 0.1073,
          "rationale": "20d momentum positive"
        },
        {
          "agent": "Ray Dalio macro/price",
          "verdict": "HOLD",
          "confidence": 75.0,
          "score": 0.35,
          "rationale": "benchmark supportive; medium-term relative momentum"
        }
      ]
    },
    {
      "symbol": "RKLB",
      "decision": "PASS",
      "target_weight": 0.0,
      "committee_score": 0.0973,
      "votes": [
        {
          "agent": "Warren Buffett value",
          "verdict": "MONITOR",
          "confidence": 38.3,
          "score": -0.03,
          "rationale": "expensive PE; debt acceptable"
        },
        {
          "agent": "Charlie Munger fundamental+news",
          "verdict": "HOLD",
          "confidence": 77.8,
          "score": 0.29,
          "rationale": "revenue growth; gross margin quality; news tone positive"
        },
        {
          "agent": "Bill Ackman fundamental+insider",
          "verdict": "MONITOR",
          "confidence": 64.2,
          "score": -0.16,
          "rationale": "insider activity skews sell"
        },
        {
          "agent": "Steve Cohen technical",
          "verdict": "HOLD",
          "confidence": 67.5,
          "score": 0.25,
          "rationale": "20d momentum positive"
        },
        {
          "agent": "Ray Dalio macro/price",
          "verdict": "MONITOR",
          "confidence": 40.0,
          "score": 0.0,
          "rationale": "benchmark supportive; high volatility haircut"
        }
      ]
    },
    {
      "symbol": "RGTI",
      "decision": "QUALITY_REJECT",
      "target_weight": 0.0,
      "committee_score": 0.0813,
      "votes": [
        {
          "agent": "Warren Buffett value",
          "verdict": "MONITOR",
          "confidence": 48.2,
          "score": 0.12,
          "rationale": "debt acceptable"
        },
        {
          "agent": "Charlie Munger fundamental+news",
          "verdict": "MONITOR",
          "confidence": 49.0,
          "score": 0.05,
          "rationale": "news tone positive"
        },
        {
          "agent": "Bill Ackman fundamental+insider",
          "verdict": "MONITOR",
          "confidence": 64.2,
          "score": -0.16,
          "rationale": "insider activity skews sell"
        },
        {
          "agent": "Steve Cohen technical",
          "verdict": "HOLD",
          "confidence": 67.5,
          "score": 0.25,
          "rationale": "20d momentum positive"
        },
        {
          "agent": "Ray Dalio macro/price",
          "verdict": "HOLD",
          "confidence": 55.0,
          "score": 0.15,
          "rationale": "benchmark supportive"
        }
      ]
    },
    {
      "symbol": "NNE",
      "decision": "QUALITY_REJECT",
      "target_weight": 0.0,
      "committee_score": 0.0643,
      "votes": [
        {
          "agent": "Warren Buffett value",
          "verdict": "MONITOR",
          "confidence": 48.2,
          "score": 0.12,
          "rationale": "debt acceptable"
        },
        {
          "agent": "Charlie Munger fundamental+news",
          "verdict": "MONITOR",
          "confidence": 55.0,
          "score": 0.1,
          "rationale": "news tone positive"
        },
        {
          "agent": "Bill Ackman fundamental+insider",
          "verdict": "MONITOR",
          "confidence": 64.2,
          "score": -0.16,
          "rationale": "insider activity skews sell"
        },
        {
          "agent": "Steve Cohen technical",
          "verdict": "HOLD",
          "confidence": 67.3,
          "score": 0.2476,
          "rationale": "20d momentum positive"
        },
        {
          "agent": "Ray Dalio macro/price",
          "verdict": "MONITOR",
          "confidence": 40.0,
          "score": 0.0,
          "rationale": "benchmark supportive; high volatility haircut"
        }
      ]
    },
    {
      "symbol": "LUNR",
      "decision": "PASS",
      "target_weight": 0.0,
      "committee_score": 0.03,
      "votes": [
        {
          "agent": "Warren Buffett value",
          "verdict": "MONITOR",
          "confidence": 51.5,
          "score": -0.15,
          "rationale": "expensive PE"
        },
        {
          "agent": "Charlie Munger fundamental+news",
          "verdict": "MONITOR",
          "confidence": 55.0,
          "score": 0.1,
          "rationale": "news tone positive"
        },
        {
          "agent": "Bill Ackman fundamental+insider",
          "verdict": "MONITOR",
          "confidence": 64.2,
          "score": -0.16,
          "rationale": "insider activity skews sell"
        },
        {
          "agent": "Steve Cohen technical",
          "verdict": "HOLD",
          "confidence": 59.0,
          "score": 0.1557,
          "rationale": "20d momentum positive"
        },
        {
          "agent": "Ray Dalio macro/price",
          "verdict": "HOLD",
          "confidence": 60.0,
          "score": 0.2,
          "rationale": "benchmark supportive; medium-term relative momentum; high volatility haircut"
        }
      ]
    },
    {
      "symbol": "CRSP",
      "decision": "QUALITY_REJECT",
      "target_weight": 0.0,
      "committee_score": 0.0281,
      "votes": [
        {
          "agent": "Warren Buffett value",
          "verdict": "MONITOR",
          "confidence": 48.2,
          "score": 0.12,
          "rationale": "debt acceptable"
        },
        {
          "agent": "Charlie Munger fundamental+news",
          "verdict": "MONITOR",
          "confidence": 49.0,
          "score": 0.05,
          "rationale": "news tone positive"
        },
        {
          "agent": "Bill Ackman fundamental+insider",
          "verdict": "MONITOR",
          "confidence": 64.2,
          "score": -0.16,
          "rationale": "insider activity skews sell"
        },
        {
          "agent": "Steve Cohen technical",
          "verdict": "MONITOR",
          "confidence": 47.3,
          "score": 0.0254,
          "rationale": "20d momentum positive"
        },
        {
          "agent": "Ray Dalio macro/price",
          "verdict": "HOLD",
          "confidence": 55.0,
          "score": 0.15,
          "rationale": "benchmark supportive"
        }
      ]
    },
    {
      "symbol": "NVVE",
      "decision": "QUALITY_REJECT",
      "target_weight": 0.0,
      "committee_score": -0.1026,
      "votes": [
        {
          "agent": "Warren Buffett value",
          "verdict": "MONITOR",
          "confidence": 50.4,
          "score": -0.14,
          "rationale": "high leverage"
        },
        {
          "agent": "Charlie Munger fundamental+news",
          "verdict": "MONITOR",
          "confidence": 59.8,
          "score": 0.14,
          "rationale": "revenue growth"
        },
        {
          "agent": "Bill Ackman fundamental+insider",
          "verdict": "PASS",
          "confidence": 78.6,
          "score": -0.28,
          "rationale": "balance sheet activism risk; insider activity skews sell"
        },
        {
          "agent": "Steve Cohen technical",
          "verdict": "MONITOR",
          "confidence": 58.5,
          "score": -0.15,
          "rationale": "weak RSI"
        },
        {
          "agent": "Ray Dalio macro/price",
          "verdict": "MONITOR",
          "confidence": 40.0,
          "score": 0.0,
          "rationale": "benchmark supportive; high volatility haircut"
        }
      ]
    }
  ],
  "discord_summary": "🧠 **AI Hedge Fund Committee** (paper-only)\nGate: `0.35` • snapshots: `{'fundamentals': 20, 'news': 20, 'insiders': 20}`\nTop paper decisions:\n• VRT: **INVEST_PAPER** | score `0.41` | SIT `0.90` | target `5.3%` | confidence-weighted score 0.41; risk=NORMAL; active_agents=5/5\n• FSLR: **INVEST_PAPER** | score `0.39` | SIT `0.56` | target `5.1%` | confidence-weighted score 0.39; risk=NORMAL; active_agents=5/5\n• AAPL: **INVEST_PAPER** | score `0.39` | SIT `0.72` | target `5.1%` | confidence-weighted score 0.39; risk=NORMAL; active_agents=5/5\n• AME: **INVEST_PAPER** | score `0.37` | SIT `0.72` | target `5.0%` | confidence-weighted score 0.37; risk=NORMAL; active_agents=5/5\n• MSFT: **INVEST_PAPER** | score `0.37` | SIT `0.42` | target `5.0%` | confidence-weighted score 0.37; risk=NORMAL; active_agents=5/5\n• SMCI: **MONITOR** | score `0.34` | SIT `0.42` | target `0.0%` | confidence-weighted score 0.34; risk=NORMAL; active_agents=5/5\n• NVDA: **MONITOR** | score `0.29` | SIT `0.56` | target `0.0%` | confidence-weighted score 0.29; risk=NORMAL; active_agents=5/5\n• IONQ: **MONITOR** | score `0.27` | SIT `0.90` | target `0.0%` | confidence-weighted score 0.27; risk=NORMAL; active_agents=5/5\nNo orders placed. Paper/research only.\n",
  "blind_evaluation": {
    "evaluation_end": "2026-04-07",
    "portfolio_return": 0.0862,
    "benchmark_return": -0.0328,
    "excess_return": 0.119,
    "picks": [
      {
        "symbol": "LUNR",
        "decision": "INVEST_PAPER",
        "target_weight": 0.0542,
        "return": 0.2819
      },
      {
        "symbol": "RKLB",
        "decision": "INVEST_PAPER",
        "target_weight": 0.0542,
        "return": -0.1095
      }
    ]
  },
  "simulation": {
    "created_at": "2026-05-02T06:45:30.465845+00:00",
    "updated_at": "2026-05-05T16:58:37.714279+00:00",
    "mode": "paper-only",
    "cash": 74676.99,
    "starting_cash": 100000.0,
    "realized_pnl": -27.71,
    "positions": {
      "MSFT": {
        "symbol": "MSFT",
        "qty": 12.117171,
        "avg_price": 414.44,
        "last_price": 409.615,
        "opened_at": "2026-05-02T06:45:32.315084+00:00",
        "target_weight": 0.0547,
        "committee_score": 0.4332,
        "sit_score": 0.58,
        "thesis": "confidence-weighted score 0.43; risk=NORMAL; active_agents=5/5",
        "stop_price": 364.7072,
        "take_profit": 538.772,
        "votes": [
          {
            "agent": "Warren Buffett value",
            "verdict": "BUY",
            "confidence": 100,
            "score": 0.7,
            "rationale": "reasonable PE; debt acceptable; positive free cash flow; ROE quality; profitable margins",
            "data_scope": [
              "fundamentals"
            ]
          },
          {
            "agent": "Charlie Munger fundamental+news",
            "verdict": "HOLD",
            "confidence": 83.2,
            "score": 0.36,
            "rationale": "revenue growth; earnings growth; gross margin quality",
            "data_scope": [
              "fundamentals",
              "news"
            ]
          },
          {
            "agent": "Bill Ackman fundamental+insider",
            "verdict": "MONITOR",
            "confidence": 61.8,
            "score": 0.14,
            "rationale": "cashflow + growth",
            "data_scope": [
              "fundamentals",
              "insider"
            ]
          },
          {
            "agent": "Steve Cohen technical",
            "verdict": "BUY",
            "confidence": 96.3,
            "score": 0.5695,
            "rationale": "bullish EMA stack; 20d momentum positive",
            "data_scope": [
              "price",
              "volume",
              "ma",
              "rsi"
            ]
          },
          {
            "agent": "Ray Dalio macro/price",
            "verdict": "HOLD",
            "confidence": 55.0,
            "score": 0.15,
            "rationale": "benchmark supportive",
            "data_scope": [
              "price",
              "benchmark",
              "volatility"
            ]
          }
        ],
        "market_value": 4963.37,
        "unrealized_pnl": -58.47,
        "unrealized_pct": -0.0116
      },
      "AAPL": {
        "symbol": "AAPL",
        "qty": 18.740629,
        "avg_price": 280.14,
        "last_price": 282.43,
        "opened_at": "2026-05-02T06:45:32.315989+00:00",
        "target_weight": 0.0525,
        "committee_score": 0.4058,
        "sit_score": 0.82,
        "thesis": "confidence-weighted score 0.41; risk=NORMAL; active_agents=5/5",
        "stop_price": 246.5232,
        "take_profit": 364.182,
        "votes": [
          {
            "agent": "Warren Buffett value",
            "verdict": "BUY",
            "confidence": 92.2,
            "score": 0.52,
            "rationale": "debt acceptable; positive free cash flow; ROE quality; profitable margins",
            "data_scope": [
              "fundamentals"
            ]
          },
          {
            "agent": "Charlie Munger fundamental+news",
            "verdict": "HOLD",
            "confidence": 89.2,
            "score": 0.41,
            "rationale": "revenue growth; earnings growth; gross margin quality; news tone positive",
            "data_scope": [
              "fundamentals",
              "news"
            ]
          },
          {
            "agent": "Bill Ackman fundamental+insider",
            "verdict": "MONITOR",
            "confidence": 47.4,
            "score": -0.02,
            "rationale": "cashflow + growth; insider activity skews sell",
            "data_scope": [
              "fundamentals",
              "insider"
            ]
          },
          {
            "agent": "Steve Cohen technical",
            "verdict": "BUY",
            "confidence": 100,
            "score": 0.6393,
            "rationale": "bullish EMA stack; 20d momentum positive; volume expansion",
            "data_scope": [
              "price",
              "volume",
              "ma",
              "rsi"
            ]
          },
          {
            "agent": "Ray Dalio macro/price",
            "verdict": "HOLD",
            "confidence": 55.0,
            "score": 0.15,
            "rationale": "benchmark supportive",
            "data_scope": [
              "price",
              "benchmark",
              "volatility"
            ]
          }
        ],
        "market_value": 5292.92,
        "unrealized_pnl": 42.92,
        "unrealized_pct": 0.0082
      },
      "VRT": {
        "symbol": "VRT",
        "qty": 15.50364,
        "avg_price": 328.31,
        "last_price": 338.85,
        "opened_at": "2026-05-02T06:45:32.316812+00:00",
        "target_weight": 0.0509,
        "committee_score": 0.3858,
        "sit_score": 0.9,
        "thesis": "confidence-weighted score 0.39; risk=NORMAL; active_agents=5/5",
        "stop_price": 288.9128,
        "take_profit": 426.803,
        "votes": [
          {
            "agent": "Warren Buffett value",
            "verdict": "HOLD",
            "confidence": 75.7,
            "score": 0.37,
            "rationale": "expensive PE; debt acceptable; positive free cash flow; ROE quality; profitable margins",
            "data_scope": [
              "fundamentals"
            ]
          },
          {
            "agent": "Charlie Munger fundamental+news",
            "verdict": "HOLD",
            "confidence": 83.2,
            "score": 0.36,
            "rationale": "revenue growth; earnings growth; gross margin quality",
            "data_scope": [
              "fundamentals",
              "news"
            ]
          },
          {
            "agent": "Bill Ackman fundamental+insider",
            "verdict": "MONITOR",
            "confidence": 61.8,
            "score": 0.14,
            "rationale": "cashflow + growth",
            "data_scope": [
              "fundamentals",
              "insider"
            ]
          },
          {
            "agent": "Steve Cohen technical",
            "verdict": "BUY",
            "confidence": 99.0,
            "score": 0.6,
            "rationale": "bullish EMA stack; 20d momentum positive",
            "data_scope": [
              "price",
              "volume",
              "ma",
              "rsi"
            ]
          },
          {
            "agent": "Ray Dalio macro/price",
            "verdict": "HOLD",
            "confidence": 75.0,
            "score": 0.35,
            "rationale": "benchmark supportive; medium-term relative momentum",
            "data_scope": [
              "price",
              "benchmark",
              "volatility"
            ]
          }
        ],
        "market_value": 5253.41,
        "unrealized_pnl": 163.41,
        "unrealized_pct": 0.0321
      },
      "FSLR": {
        "symbol": "FSLR",
        "qty": 23.333805,
        "avg_price": 211.71,
        "last_price": 218.14,
        "opened_at": "2026-05-02T06:45:32.317065+00:00",
        "target_weight": 0.0494,
        "committee_score": 0.367,
        "sit_score": 0.52,
        "thesis": "confidence-weighted score 0.37; risk=NORMAL; active_agents=5/5",
        "stop_price": 186.3048,
        "take_profit": 275.223,
        "votes": [
          {
            "agent": "Warren Buffett value",
            "verdict": "BUY",
            "confidence": 100,
            "score": 0.7,
            "rationale": "reasonable PE; debt acceptable; positive free cash flow; ROE quality; profitable margins",
            "data_scope": [
              "fundamentals"
            ]
          },
          {
            "agent": "Charlie Munger fundamental+news",
            "verdict": "HOLD",
            "confidence": 89.2,
            "score": 0.41,
            "rationale": "revenue growth; earnings growth; gross margin quality; news tone positive",
            "data_scope": [
              "fundamentals",
              "news"
            ]
          },
          {
            "agent": "Bill Ackman fundamental+insider",
            "verdict": "MONITOR",
            "confidence": 47.4,
            "score": -0.02,
            "rationale": "cashflow + growth; insider activity skews sell",
            "data_scope": [
              "fundamentals",
              "insider"
            ]
          },
          {
            "agent": "Steve Cohen technical",
            "verdict": "HOLD",
            "confidence": 69.1,
            "score": 0.2678,
            "rationale": "20d momentum positive; volume expansion",
            "data_scope": [
              "price",
              "volume",
              "ma",
              "rsi"
            ]
          },
          {
            "agent": "Ray Dalio macro/price",
            "verdict": "HOLD",
            "confidence": 55.0,
            "score": 0.15,
            "rationale": "benchmark supportive",
            "data_scope": [
              "price",
              "benchmark",
              "volatility"
            ]
          }
        ],
        "market_value": 5090.04,
        "unrealized_pnl": 150.04,
        "unrealized_pct": 0.0304
      },
      "AME": {
        "symbol": "AME",
        "qty": 21.071213,
        "avg_price": 236.98,
        "last_price": 236.98,
        "opened_at": "2026-05-05T16:58:37.713826+00:00",
        "target_weight": 0.0498,
        "committee_score": 0.3729,
        "sit_score": 0.72,
        "thesis": "confidence-weighted score 0.37; risk=NORMAL; active_agents=5/5",
        "stop_price": 208.5424,
        "take_profit": 308.074,
        "votes": [
          {
            "agent": "Warren Buffett value",
            "verdict": "BUY",
            "confidence": 92.2,
            "score": 0.52,
            "rationale": "debt acceptable; positive free cash flow; ROE quality; profitable margins",
            "data_scope": [
              "fundamentals"
            ]
          },
          {
            "agent": "Charlie Munger fundamental+news",
            "verdict": "HOLD",
            "confidence": 86.2,
            "score": 0.36,
            "rationale": "revenue growth; earnings growth; gross margin quality",
            "data_scope": [
              "fundamentals",
              "news"
            ]
          },
          {
            "agent": "Bill Ackman fundamental+insider",
            "verdict": "MONITOR",
            "confidence": 61.8,
            "score": 0.14,
            "rationale": "cashflow + growth",
            "data_scope": [
              "fundamentals",
              "insider"
            ]
          },
          {
            "agent": "Steve Cohen technical",
            "verdict": "BUY",
            "confidence": 92.4,
            "score": 0.5266,
            "rationale": "bullish EMA stack; 20d momentum positive",
            "data_scope": [
              "price",
              "volume",
              "ma",
              "rsi"
            ]
          },
          {
            "agent": "Ray Dalio macro/price",
            "verdict": "HOLD",
            "confidence": 55.0,
            "score": 0.15,
            "rationale": "benchmark supportive",
            "data_scope": [
              "price",
              "benchmark",
              "volatility"
            ]
          }
        ],
        "market_value": 4993.46,
        "unrealized_pnl": -0.0,
        "unrealized_pct": -0.0
      }
    },
    "equity_history": [
      {
        "timestamp": "2026-05-02T06:45:32.317456+00:00",
        "equity": 100000.0,
        "cash": 74000.0,
        "market_value": 26000.0,
        "unrealized_pnl": 0.0,
        "realized_pnl": 0.0,
        "total_return": 0.0,
        "positions": 5
      },
      {
        "timestamp": "2026-05-05T16:58:37.714273+00:00",
        "equity": 100270.19,
        "cash": 74676.99,
        "market_value": 25593.2,
        "unrealized_pnl": 297.9,
        "realized_pnl": -27.71,
        "total_return": 0.0027,
        "positions": 5
      }
    ],
    "last_committee_generated_at": "2026-05-05T16:58:35.048182+00:00",
    "risk": {
      "max_gross_exposure": 0.35,
      "max_position_weight": 0.08,
      "stop_loss_pct": 0.12,
      "take_profit_pct": 0.3
    },
    "market_value": 25593.2,
    "unrealized_pnl": 297.9,
    "equity": 100270.19,
    "total_return": 0.0027,
    "last_orders": [
      {
        "timestamp": "2026-05-05T16:58:37.713039+00:00",
        "symbol": "NVDA",
        "side": "SELL",
        "qty": 26.455027,
        "price": 197.6,
        "value": 5227.51,
        "reason": "committee no longer INVEST_PAPER",
        "mode": "paper",
        "realized_pnl": -22.49
      },
      {
        "timestamp": "2026-05-05T16:58:37.713835+00:00",
        "symbol": "AME",
        "side": "BUY",
        "qty": 21.071213,
        "price": 236.98,
        "value": 4993.46,
        "reason": "AIHF committee INVEST_PAPER",
        "mode": "paper",
        "committee_score": 0.3729,
        "target_weight": 0.0498
      },
      {
        "timestamp": "2026-05-05T16:58:37.714062+00:00",
        "symbol": "MSFT",
        "side": "TRIM",
        "qty": 1.081362,
        "price": 409.615,
        "value": 442.94,
        "reason": "rebalance target lower",
        "mode": "paper",
        "realized_pnl": -5.22
      }
    ]
  },
  "alpaca_live": {
    "updated_at": "2026-05-11T13:40:06.430199+00:00",
    "aihf_symbols": [
      "AAPL",
      "AME",
      "FSLR",
      "MSFT",
      "VRT"
    ],
    "last_execution": {
      "generated_at": "2026-05-11T13:40:06.430158+00:00",
      "mode": "alpaca-paper-live",
      "paper_base_url": "https://paper-api.alpaca.markets",
      "equity": 90253.25,
      "max_equity_pct": 0.1,
      "max_position_pct": 0.02,
      "committee_generated_at": "2026-05-05T16:58:35.048182+00:00",
      "kronos_filter_enabled": false,
      "paper_leverage_enabled": false,
      "actions": [
        {
          "action": "buy_bracket",
          "symbol": "VRT",
          "notional": 1805.07,
          "price": 349.04,
          "kronos": {
            "symbol": "VRT",
            "last_price": 339.9700012207031,
            "direction": "UP",
            "expected_move_5d": 0.09008515842945401,
            "volatility_5d": 0.07724148888022274,
            "atr_pct": 0.04822316304163431,
            "confidence": 0.7565814711988852,
            "model": "kronos_proxy_shadow",
            "features": {
              "mom_5": 0.03551522569771404,
              "mom_20": 0.1520111758187348,
              "ema20_vs_ema50": 0.10449697664462754
            },
            "alignment_score": 0.8905,
            "paper_leverage_multiplier": 0.23,
            "opinion": "ALLOW",
            "paper_leverage_enabled": false,
            "max_risk_per_trade_pct": 0.003
          },
          "result": {
            "id": "4f0eab27-ba0a-40ad-8e04-ece1d7dff98f",
            "client_order_id": "AIHF-VRT-20260511134002",
            "created_at": "2026-05-11T13:40:01.624965254Z",
            "updated_at": "2026-05-11T13:40:01.630227414Z",
            "submitted_at": "2026-05-11T13:40:01.624965254Z",
            "filled_at": null,
            "expired_at": null,
            "canceled_at": null,
            "failed_at": null,
            "replaced_at": null,
            "replaced_by": null,
            "replaces": null,
            "asset_id": "a0026393-53a9-454c-89f9-1eb7cb4ae7af",
            "symbol": "VRT",
            "asset_class": "us_equity",
            "notional": null,
            "qty": "5",
            "filled_qty": "0",
            "filled_avg_price": null,
            "order_class": "bracket",
            "order_type": "market",
            "type": "market",
            "side": "buy",
            "position_intent": "buy_to_open",
            "time_in_force": "day",
            "limit_price": null,
            "stop_price": null,
            "status": "pending_new",
            "extended_hours": false,
            "legs": [
              {
                "id": "88bd34b3-3dd4-4759-8d0a-6e5082252226",
                "client_order_id": "3bc16850-cccb-4e68-bb75-7ce51ae4713a",
                "created_at": "2026-05-11T13:40:01.624965254Z",
                "updated_at": "2026-05-11T13:40:01.630188074Z",
                "submitted_at": "2026-05-11T13:40:01.624965254Z",
                "filled_at": null,
                "expired_at": null,
                "canceled_at": null,
                "failed_at": null,
                "replaced_at": null,
                "replaced_by": null,
                "replaces": null,
                "asset_id": "a0026393-53a9-454c-89f9-1eb7cb4ae7af",
                "symbol": "VRT",
                "asset_class": "us_equity",
                "notional": null,
                "qty": "5",
                "filled_qty": "0",
                "filled_avg_price": null,
                "order_class": "bracket",
                "order_type": "limit",
                "type": "limit",
                "side": "sell",
                "position_intent": "sell_to_close",
                "time_in_force": "day",
                "limit_price": "436.29",
                "stop_price": null,
                "status": "held",
                "extended_hours": false,
                "legs": null,
                "trail_percent": null,
                "trail_price": null,
                "hwm": null,
                "subtag": null,
                "source": null,
                "expires_at": "2026-05-11T20:00:00Z"
              },
              {
                "id": "676c9013-9048-436c-9580-aa8cd6a3f53d",
                "client_order_id": "e9a54baf-6ac8-4b69-8643-4b053817a6e8",
                "created_at": "2026-05-11T13:40:01.624965254Z",
                "updated_at": "2026-05-11T13:40:01.630205354Z",
                "submitted_at": "2026-05-11T13:40:01.624965254Z",
                "filled_at": null,
                "expired_at": null,
                "canceled_at": null,
                "failed_at": null,
                "replaced_at": null,
                "replaced_by": null,
                "replaces": null,
                "asset_id": "a0026393-53a9-454c-89f9-1eb7cb4ae7af",
                "symbol": "VRT",
                "asset_class": "us_equity",
                "notional": null,
                "qty": "5",
                "filled_qty": "0",
                "filled_avg_price": null,
                "order_class": "bracket",
                "order_type": "stop",
                "type": "stop",
                "side": "sell",
                "position_intent": "sell_to_close",
                "time_in_force": "day",
                "limit_price": null,
                "stop_price": "314.13",
                "status": "held",
                "extended_hours": false,
                "legs": null,
                "trail_percent": null,
                "trail_price": null,
                "hwm": null,
                "subtag": null,
                "source": null,
                "expires_at": "2026-05-11T20:00:00Z"
              }
            ],
            "trail_percent": null,
            "trail_price": null,
            "hwm": null,
            "subtag": null,
            "source": null,
            "expires_at": "2026-05-11T20:00:00Z"
          }
        },
        {
          "action": "buy_bracket",
          "symbol": "FSLR",
          "notional": 1805.07,
          "price": 227.23,
          "kronos": {
            "symbol": "FSLR",
            "last_price": 219.9499969482422,
            "direction": "UP",
            "expected_move_5d": 0.04552693217644742,
            "volatility_5d": 0.059041522585169606,
            "atr_pct": 0.04386386815129587,
            "confidence": 0.6696420525803698,
            "model": "kronos_proxy_shadow",
            "features": {
              "mom_5": 0.0389211183839393,
              "mom_20": 0.08099471975558337,
              "ema20_vs_ema50": -0.0016786150538972144
            },
            "alignment_score": 0.7254,
            "paper_leverage_multiplier": 0.3,
            "opinion": "ALLOW",
            "paper_leverage_enabled": false,
            "max_risk_per_trade_pct": 0.003
          },
          "result": {
            "id": "59f2604a-9753-437b-a8ea-06fa36fb5771",
            "client_order_id": "AIHF-FSLR-20260511134003",
            "created_at": "2026-05-11T13:40:02.511749337Z",
            "updated_at": "2026-05-11T13:40:02.513985067Z",
            "submitted_at": "2026-05-11T13:40:02.511749337Z",
            "filled_at": null,
            "expired_at": null,
            "canceled_at": null,
            "failed_at": null,
            "replaced_at": null,
            "replaced_by": null,
            "replaces": null,
            "asset_id": "fa06daac-c3f1-409c-bddb-d44c8293e8b3",
            "symbol": "FSLR",
            "asset_class": "us_equity",
            "notional": null,
            "qty": "7",
            "filled_qty": "0",
            "filled_avg_price": null,
            "order_class": "bracket",
            "order_type": "market",
            "type": "market",
            "side": "buy",
            "position_intent": "buy_to_open",
            "time_in_force": "day",
            "limit_price": null,
            "stop_price": null,
            "status": "pending_new",
            "extended_hours": false,
            "legs": [
              {
                "id": "243a0954-0f65-48d5-8fae-df3959ad5b2b",
                "client_order_id": "993164ec-a7eb-4483-b43e-ed85b6fc2320",
                "created_at": "2026-05-11T13:40:02.511749337Z",
                "updated_at": "2026-05-11T13:40:02.513936127Z",
                "submitted_at": "2026-05-11T13:40:02.511749337Z",
                "filled_at": null,
                "expired_at": null,
                "canceled_at": null,
                "failed_at": null,
                "replaced_at": null,
                "replaced_by": null,
                "replaces": null,
                "asset_id": "fa06daac-c3f1-409c-bddb-d44c8293e8b3",
                "symbol": "FSLR",
                "asset_class": "us_equity",
                "notional": null,
                "qty": "7",
                "filled_qty": "0",
                "filled_avg_price": null,
                "order_class": "bracket",
                "order_type": "limit",
                "type": "limit",
                "side": "sell",
                "position_intent": "sell_to_close",
                "time_in_force": "day",
                "limit_price": "284.04",
                "stop_price": null,
                "status": "held",
                "extended_hours": false,
                "legs": null,
                "trail_percent": null,
                "trail_price": null,
                "hwm": null,
                "subtag": null,
                "source": null,
                "expires_at": "2026-05-11T20:00:00Z"
              },
              {
                "id": "7aa4dd97-6a89-4f07-9bcc-54880c550b0b",
                "client_order_id": "937c54fc-2395-48b1-9110-b3739dff8429",
                "created_at": "2026-05-11T13:40:02.511749337Z",
                "updated_at": "2026-05-11T13:40:02.513958587Z",
                "submitted_at": "2026-05-11T13:40:02.511749337Z",
                "filled_at": null,
                "expired_at": null,
                "canceled_at": null,
                "failed_at": null,
                "replaced_at": null,
                "replaced_by": null,
                "replaces": null,
                "asset_id": "fa06daac-c3f1-409c-bddb-d44c8293e8b3",
                "symbol": "FSLR",
                "asset_class": "us_equity",
                "notional": null,
                "qty": "7",
                "filled_qty": "0",
                "filled_avg_price": null,
                "order_class": "bracket",
                "order_type": "stop",
                "type": "stop",
                "side": "sell",
                "position_intent": "sell_to_close",
                "time_in_force": "day",
                "limit_price": null,
                "stop_price": "204.51",
                "status": "held",
                "extended_hours": false,
                "legs": null,
                "trail_percent": null,
                "trail_price": null,
                "hwm": null,
                "subtag": null,
                "source": null,
                "expires_at": "2026-05-11T20:00:00Z"
              }
            ],
            "trail_percent": null,
            "trail_price": null,
            "hwm": null,
            "subtag": null,
            "source": null,
            "expires_at": "2026-05-11T20:00:00Z"
          }
        },
        {
          "action": "buy_bracket",
          "symbol": "AAPL",
          "notional": 1805.07,
          "price": 291.0,
          "kronos": {
            "symbol": "AAPL",
            "last_price": 293.32000732421875,
            "direction": "UP",
            "expected_move_5d": 0.07065806361256455,
            "volatility_5d": 0.03709901181967791,
            "atr_pct": 0.023604154958853648,
            "confidence": 0.9190077641507153,
            "model": "kronos_proxy_shadow",
            "features": {
              "mom_5": 0.04704787601414795,
              "mom_20": 0.12607491919836522,
              "ema20_vs_ema50": 0.026801488433850773
            },
            "alignment_score": 0.9636,
            "paper_leverage_multiplier": 0.49,
            "opinion": "ALLOW",
            "paper_leverage_enabled": false,
            "max_risk_per_trade_pct": 0.003
          },
          "result": {
            "id": "b3e39573-87fc-4d74-8a3b-92a4bee8d656",
            "client_order_id": "AIHF-AAPL-20260511134004",
            "created_at": "2026-05-11T13:40:03.353745509Z",
            "updated_at": "2026-05-11T13:40:03.360595279Z",
            "submitted_at": "2026-05-11T13:40:03.353745509Z",
            "filled_at": null,
            "expired_at": null,
            "canceled_at": null,
            "failed_at": null,
            "replaced_at": null,
            "replaced_by": null,
            "replaces": null,
            "asset_id": "b0b6dd9d-8b9b-48a9-ba46-b9d54906e415",
            "symbol": "AAPL",
            "asset_class": "us_equity",
            "notional": null,
            "qty": "6",
            "filled_qty": "0",
            "filled_avg_price": null,
            "order_class": "bracket",
            "order_type": "market",
            "type": "market",
            "side": "buy",
            "position_intent": "buy_to_open",
            "time_in_force": "day",
            "limit_price": null,
            "stop_price": null,
            "status": "pending_new",
            "extended_hours": false,
            "legs": [
              {
                "id": "4dc179f7-a445-4110-9a01-ef7059207329",
                "client_order_id": "11fa7dc2-8128-4f74-a2e6-aae21ebef05e",
                "created_at": "2026-05-11T13:40:03.353745509Z",
                "updated_at": "2026-05-11T13:40:03.360562279Z",
                "submitted_at": "2026-05-11T13:40:03.353745509Z",
                "filled_at": null,
                "expired_at": null,
                "canceled_at": null,
                "failed_at": null,
                "replaced_at": null,
                "replaced_by": null,
                "replaces": null,
                "asset_id": "b0b6dd9d-8b9b-48a9-ba46-b9d54906e415",
                "symbol": "AAPL",
                "asset_class": "us_equity",
                "notional": null,
                "qty": "6",
                "filled_qty": "0",
                "filled_avg_price": null,
                "order_class": "bracket",
                "order_type": "limit",
                "type": "limit",
                "side": "sell",
                "position_intent": "sell_to_close",
                "time_in_force": "day",
                "limit_price": "363.75",
                "stop_price": null,
                "status": "held",
                "extended_hours": false,
                "legs": null,
                "trail_percent": null,
                "trail_price": null,
                "hwm": null,
                "subtag": null,
                "source": null,
                "expires_at": "2026-05-11T20:00:00Z"
              },
              {
                "id": "72b68d07-98e9-48b1-bb95-16b8de0e8588",
                "client_order_id": "426e92fe-1aef-47e8-8194-afe5c694fdaa",
                "created_at": "2026-05-11T13:40:03.353745509Z",
                "updated_at": "2026-05-11T13:40:03.360577459Z",
                "submitted_at": "2026-05-11T13:40:03.353745509Z",
                "filled_at": null,
                "expired_at": null,
                "canceled_at": null,
                "failed_at": null,
                "replaced_at": null,
                "replaced_by": null,
                "replaces": null,
                "asset_id": "b0b6dd9d-8b9b-48a9-ba46-b9d54906e415",
                "symbol": "AAPL",
                "asset_class": "us_equity",
                "notional": null,
                "qty": "6",
                "filled_qty": "0",
                "filled_avg_price": null,
                "order_class": "bracket",
                "order_type": "stop",
                "type": "stop",
                "side": "sell",
                "position_intent": "sell_to_close",
                "time_in_force": "day",
                "limit_price": null,
                "stop_price": "261.9",
                "status": "held",
                "extended_hours": false,
                "legs": null,
                "trail_percent": null,
                "trail_price": null,
                "hwm": null,
                "subtag": null,
                "source": null,
                "expires_at": "2026-05-11T20:00:00Z"
              }
            ],
            "trail_percent": null,
            "trail_price": null,
            "hwm": null,
            "subtag": null,
            "source": null,
            "expires_at": "2026-05-11T20:00:00Z"
          }
        },
        {
          "action": "buy_bracket",
          "symbol": "AME",
          "notional": 1805.07,
          "price": 232.11,
          "kronos": {
            "symbol": "AME",
            "last_price": 232.39999389648438,
            "direction": "FLAT",
            "expected_move_5d": 0.003574945350846121,
            "volatility_5d": 0.03897504980875961,
            "atr_pct": 0.02854685205301722,
            "confidence": 0.5201792680457173,
            "model": "kronos_proxy_shadow",
            "features": {
              "mom_5": 0.008330433029055673,
              "mom_20": -0.010684984574924061,
              "ema20_vs_ema50": 0.017829975444972446
            },
            "alignment_score": 0.2845,
            "paper_leverage_multiplier": 0.46,
            "opinion": "FILTER_OR_REDUCE",
            "paper_leverage_enabled": false,
            "max_risk_per_trade_pct": 0.003
          },
          "result": {
            "id": "f95a8f4c-b7b4-4807-a7ee-8d31b6ce2eca",
            "client_order_id": "AIHF-AME-20260511134005",
            "created_at": "2026-05-11T13:40:04.214252632Z",
            "updated_at": "2026-05-11T13:40:04.220674192Z",
            "submitted_at": "2026-05-11T13:40:04.214252632Z",
            "filled_at": null,
            "expired_at": null,
            "canceled_at": null,
            "failed_at": null,
            "replaced_at": null,
            "replaced_by": null,
            "replaces": null,
            "asset_id": "6642e128-03ee-4bc9-bd3f-8f49424480d7",
            "symbol": "AME",
            "asset_class": "us_equity",
            "notional": null,
            "qty": "7",
            "filled_qty": "0",
            "filled_avg_price": null,
            "order_class": "bracket",
            "order_type": "market",
            "type": "market",
            "side": "buy",
            "position_intent": "buy_to_open",
            "time_in_force": "day",
            "limit_price": null,
            "stop_price": null,
            "status": "pending_new",
            "extended_hours": false,
            "legs": [
              {
                "id": "e09bc739-becc-4d8d-8a5c-8396a75a5e81",
                "client_order_id": "bfea72d4-bb94-4ddd-a107-750469af9763",
                "created_at": "2026-05-11T13:40:04.214252632Z",
                "updated_at": "2026-05-11T13:40:04.220622502Z",
                "submitted_at": "2026-05-11T13:40:04.214252632Z",
                "filled_at": null,
                "expired_at": null,
                "canceled_at": null,
                "failed_at": null,
                "replaced_at": null,
                "replaced_by": null,
                "replaces": null,
                "asset_id": "6642e128-03ee-4bc9-bd3f-8f49424480d7",
                "symbol": "AME",
                "asset_class": "us_equity",
                "notional": null,
                "qty": "7",
                "filled_qty": "0",
                "filled_avg_price": null,
                "order_class": "bracket",
                "order_type": "limit",
                "type": "limit",
                "side": "sell",
                "position_intent": "sell_to_close",
                "time_in_force": "day",
                "limit_price": "290.14",
                "stop_price": null,
                "status": "held",
                "extended_hours": false,
                "legs": null,
                "trail_percent": null,
                "trail_price": null,
                "hwm": null,
                "subtag": null,
                "source": null,
                "expires_at": "2026-05-11T20:00:00Z"
              },
              {
                "id": "a4275b51-16d0-447f-9479-28b934bb3792",
                "client_order_id": "b287cec6-e089-4a4b-a05f-810da7fa05e8",
                "created_at": "2026-05-11T13:40:04.214252632Z",
                "updated_at": "2026-05-11T13:40:04.220644472Z",
                "submitted_at": "2026-05-11T13:40:04.214252632Z",
                "filled_at": null,
                "expired_at": null,
                "canceled_at": null,
                "failed_at": null,
                "replaced_at": null,
                "replaced_by": null,
                "replaces": null,
                "asset_id": "6642e128-03ee-4bc9-bd3f-8f49424480d7",
                "symbol": "AME",
                "asset_class": "us_equity",
                "notional": null,
                "qty": "7",
                "filled_qty": "0",
                "filled_avg_price": null,
                "order_class": "bracket",
                "order_type": "stop",
                "type": "stop",
                "side": "sell",
                "position_intent": "sell_to_close",
                "time_in_force": "day",
                "limit_price": null,
                "stop_price": "208.9",
                "status": "held",
                "extended_hours": false,
                "legs": null,
                "trail_percent": null,
                "trail_price": null,
                "hwm": null,
                "subtag": null,
                "source": null,
                "expires_at": "2026-05-11T20:00:00Z"
              }
            ],
            "trail_percent": null,
            "trail_price": null,
            "hwm": null,
            "subtag": null,
            "source": null,
            "expires_at": "2026-05-11T20:00:00Z"
          }
        },
        {
          "action": "buy_bracket",
          "symbol": "MSFT",
          "notional": 1805.07,
          "price": 410.4,
          "kronos": {
            "symbol": "MSFT",
            "last_price": 415.1199951171875,
            "direction": "UP",
            "expected_move_5d": 0.04448361232012365,
            "volatility_5d": 0.04907493124130711,
            "atr_pct": 0.028490904357683866,
            "confidence": 0.6994173901600874,
            "model": "kronos_proxy_shadow",
            "features": {
              "mom_5": 0.0016407505833788694,
              "mom_20": 0.11931404692368797,
              "ema20_vs_ema50": 0.00992679067156188
            },
            "alignment_score": 0.8133,
            "paper_leverage_multiplier": 0.37,
            "opinion": "ALLOW",
            "paper_leverage_enabled": false,
            "max_risk_per_trade_pct": 0.003
          },
          "result": {
            "id": "d1df3d5b-1959-41f4-bff2-38c06dc06825",
            "client_order_id": "AIHF-MSFT-20260511134006",
            "created_at": "2026-05-11T13:40:05.076778755Z",
            "updated_at": "2026-05-11T13:40:05.083371505Z",
            "submitted_at": "2026-05-11T13:40:05.076778755Z",
            "filled_at": null,
            "expired_at": null,
            "canceled_at": null,
            "failed_at": null,
            "replaced_at": null,
            "replaced_by": null,
            "replaces": null,
            "asset_id": "b6d1aa75-5c9c-4353-a305-9e2caa1925ab",
            "symbol": "MSFT",
            "asset_class": "us_equity",
            "notional": null,
            "qty": "4",
            "filled_qty": "0",
            "filled_avg_price": null,
            "order_class": "bracket",
            "order_type": "market",
            "type": "market",
            "side": "buy",
            "position_intent": "buy_to_open",
            "time_in_force": "day",
            "limit_price": null,
            "stop_price": null,
            "status": "pending_new",
            "extended_hours": false,
            "legs": [
              {
                "id": "6d6b0bff-beb6-42e0-9e68-bf0b3869f3a6",
                "client_order_id": "51332c16-1378-4bad-a16f-d13d0207e590",
                "created_at": "2026-05-11T13:40:05.076778755Z",
                "updated_at": "2026-05-11T13:40:05.083298585Z",
                "submitted_at": "2026-05-11T13:40:05.076778755Z",
                "filled_at": null,
                "expired_at": null,
                "canceled_at": null,
                "failed_at": null,
                "replaced_at": null,
                "replaced_by": null,
                "replaces": null,
                "asset_id": "b6d1aa75-5c9c-4353-a305-9e2caa1925ab",
                "symbol": "MSFT",
                "asset_class": "us_equity",
                "notional": null,
                "qty": "4",
                "filled_qty": "0",
                "filled_avg_price": null,
                "order_class": "bracket",
                "order_type": "limit",
                "type": "limit",
                "side": "sell",
                "position_intent": "sell_to_close",
                "time_in_force": "day",
                "limit_price": "513",
                "stop_price": null,
                "status": "held",
                "extended_hours": false,
                "legs": null,
                "trail_percent": null,
                "trail_price": null,
                "hwm": null,
                "subtag": null,
                "source": null,
                "expires_at": "2026-05-11T20:00:00Z"
              },
              {
                "id": "ace2f4df-6de7-4aec-8c0c-474fcbef30b8",
                "client_order_id": "5df5a118-03a3-4483-8922-0f9aed7972e1",
                "created_at": "2026-05-11T13:40:05.076778755Z",
                "updated_at": "2026-05-11T13:40:05.083322205Z",
                "submitted_at": "2026-05-11T13:40:05.076778755Z",
                "filled_at": null,
                "expired_at": null,
                "canceled_at": null,
                "failed_at": null,
                "replaced_at": null,
                "replaced_by": null,
                "replaces": null,
                "asset_id": "b6d1aa75-5c9c-4353-a305-9e2caa1925ab",
                "symbol": "MSFT",
                "asset_class": "us_equity",
                "notional": null,
                "qty": "4",
                "filled_qty": "0",
                "filled_avg_price": null,
                "order_class": "bracket",
                "order_type": "stop",
                "type": "stop",
                "side": "sell",
                "position_intent": "sell_to_close",
                "time_in_force": "day",
                "limit_price": null,
                "stop_price": "369.36",
                "status": "held",
                "extended_hours": false,
                "legs": null,
                "trail_percent": null,
                "trail_price": null,
                "hwm": null,
                "subtag": null,
                "source": null,
                "expires_at": "2026-05-11T20:00:00Z"
              }
            ],
            "trail_percent": null,
            "trail_price": null,
            "hwm": null,
            "subtag": null,
            "source": null,
            "expires_at": "2026-05-11T20:00:00Z"
          }
        }
      ]
    }
  },
  "execution_model_note": "Simulation is a local research shadow book. Alpaca Paper Live is the broker paper account and is the primary live-paper track. Results differ because of start date, account equity, whole-share/bracket fills, and existing account positions.",
  "caveat": "AIHF is Alpaca PAPER only. Simulation and broker paper are separated deliberately."
}