{
  "count": 3,
  "total_unrealized_pl": 119.23,
  "longs": 3,
  "shorts": 0,
  "rows": [
    {
      "symbol": "XRPUSD",
      "side": "long",
      "qty": 642.902496,
      "avg_entry_price": 1.103,
      "current_price": 1.143,
      "market_value": 734.837553,
      "cost_basis": 709.121453,
      "unrealized_pl": 25.7161,
      "unrealized_plpc": 3.63,
      "change_today": 4.77,
      "asset_class": "crypto",
      "engine": "crypto_john",
      "engine_label": "Crypto John Live",
      "stop_loss": 1.38,
      "take_profit": 1.46,
      "opened_at": "2026-05-07T00:45:22.000472+02:00",
      "protection": "protected",
      "protection_orders": 0,
      "stop_prices": []
    },
    {
      "symbol": "ETHUSD",
      "side": "long",
      "qty": 1.03611552,
      "avg_entry_price": 1709.62,
      "current_price": 1750.28,
      "market_value": 1813.492272,
      "cost_basis": 1771.363815,
      "unrealized_pl": 42.128457,
      "unrealized_plpc": 2.38,
      "change_today": 2.26,
      "asset_class": "crypto",
      "engine": "crypto_john",
      "engine_label": "Crypto John Live",
      "stop_loss": 2273.46,
      "take_profit": 2391.29,
      "opened_at": "2026-05-09T02:45:16.808660+02:00",
      "protection": "protected",
      "protection_orders": 0,
      "stop_prices": []
    },
    {
      "symbol": "ADAUSD",
      "side": "long",
      "qty": 4284.70287,
      "avg_entry_price": 0.16565,
      "current_price": 0.177642,
      "market_value": 761.143187,
      "cost_basis": 709.76103,
      "unrealized_pl": 51.382157,
      "unrealized_plpc": 7.24,
      "change_today": 7.71,
      "asset_class": "crypto",
      "engine": "crypto_john",
      "engine_label": "Crypto John Live",
      "stop_loss": 0.25,
      "take_profit": 0.26,
      "opened_at": "2026-05-03T17:45:19.520789+02:00",
      "protection": "protected",
      "protection_orders": 0,
      "stop_prices": []
    }
  ],
  "protected_count": 3,
  "missing_stop_count": 0,
  "stale_journal_opens": [
    {
      "symbol": "AVAX/USD",
      "engine": "crypto_24_7",
      "engine_label": "Crypto 24/7",
      "side": "buy",
      "entry_price": 9.359999656677246,
      "qty": 53.418805378193525,
      "opened_at": "2026-04-26T00:35:18.513732+02:00",
      "stop_loss": 9.21,
      "take_profit": 9.62
    },
    {
      "symbol": "AMZN",
      "engine": "C",
      "engine_label": "Engine C, ORB",
      "side": "sell",
      "entry_price": 259.48,
      "qty": 4,
      "opened_at": "2026-04-30T15:58:36.101109+02:00",
      "stop_loss": 263.37,
      "take_profit": 250.4
    },
    {
      "symbol": "META",
      "engine": "C",
      "engine_label": "Engine C, ORB",
      "side": "sell",
      "entry_price": 602.75,
      "qty": 2,
      "opened_at": "2026-04-30T15:58:43.610097+02:00",
      "stop_loss": 611.79,
      "take_profit": 581.65
    },
    {
      "symbol": "AMD",
      "engine": "C",
      "engine_label": "Engine C, ORB",
      "side": "buy",
      "entry_price": 345.01,
      "qty": 3,
      "opened_at": "2026-04-30T16:05:14.372393+02:00",
      "stop_loss": 339.83,
      "take_profit": 357.09
    },
    {
      "symbol": "DOT/USD",
      "engine": "crypto_24_7",
      "engine_label": "Crypto 24/7",
      "side": "buy",
      "entry_price": 1.2059999704360962,
      "qty": 414.5937083391447,
      "opened_at": "2026-05-01T14:18:05.306536+02:00",
      "stop_loss": 1.19,
      "take_profit": 1.24
    },
    {
      "symbol": "SOL/USD",
      "engine": "crypto_24_7",
      "engine_label": "Crypto 24/7",
      "side": "buy",
      "entry_price": 84.37000274658203,
      "qty": 5.926276919793698,
      "opened_at": "2026-05-01T14:48:02.332210+02:00",
      "stop_loss": 83.02,
      "take_profit": 87.32
    },
    {
      "symbol": "MSFT",
      "engine": "C",
      "engine_label": "Engine C, ORB",
      "side": "buy",
      "entry_price": 413.69,
      "qty": 2,
      "opened_at": "2026-05-01T15:54:19.610175+02:00",
      "stop_loss": 407.48,
      "take_profit": 428.17
    },
    {
      "symbol": "META",
      "engine": "C",
      "engine_label": "Engine C, ORB",
      "side": "sell",
      "entry_price": 612.505,
      "qty": 1,
      "opened_at": "2026-05-01T15:54:40.666587+02:00",
      "stop_loss": 621.69,
      "take_profit": 591.07
    },
    {
      "symbol": "AMD",
      "engine": "C",
      "engine_label": "Engine C, ORB",
      "side": "sell",
      "entry_price": 345.46,
      "qty": 2,
      "opened_at": "2026-05-05T16:16:25.273295+02:00",
      "stop_loss": 350.64,
      "take_profit": 333.37
    },
    {
      "symbol": "AMZN",
      "engine": "C",
      "engine_label": "Engine C, ORB",
      "side": "buy",
      "entry_price": 274.94,
      "qty": 3,
      "opened_at": "2026-05-05T16:16:29.366978+02:00",
      "stop_loss": 270.82,
      "take_profit": 284.56
    },
    {
      "symbol": "META",
      "engine": "C",
      "engine_label": "Engine C, ORB",
      "side": "sell",
      "entry_price": 604.42,
      "qty": 1,
      "opened_at": "2026-05-05T16:16:32.718237+02:00",
      "stop_loss": 613.49,
      "take_profit": 583.27
    },
    {
      "symbol": "XLE",
      "engine": "C",
      "engine_label": "Engine C, ORB",
      "side": "buy",
      "entry_price": 59.625,
      "qty": 15,
      "opened_at": "2026-05-05T16:16:37.444561+02:00",
      "stop_loss": 58.73,
      "take_profit": 61.71
    },
    {
      "symbol": "NVDA",
      "engine": "C",
      "engine_label": "Engine C, ORB",
      "side": "buy",
      "entry_price": 203.23,
      "qty": 5,
      "opened_at": "2026-05-06T16:07:46.942229+02:00",
      "stop_loss": 200.18,
      "take_profit": 210.34
    }
  ]
}