[
  {
    "engine": "A",
    "label": "Engine A",
    "last_run": null,
    "last_signal": null,
    "last_skip": null,
    "status": "ok",
    "last_trade_at": null,
    "health_state": "active",
    "why_no_trade": "No trade yet",
    "size_multiplier": null,
    "recent_pnl": 0.0,
    "recent_win_rate": 0
  },
  {
    "engine": "B",
    "label": "Engine B",
    "last_run": null,
    "last_signal": null,
    "last_skip": null,
    "status": "ok",
    "last_trade_at": null,
    "health_state": "active",
    "why_no_trade": "No trade yet",
    "size_multiplier": null,
    "recent_pnl": 0.0,
    "recent_win_rate": 0
  },
  {
    "engine": "daytrading",
    "label": "Daytrading",
    "last_run": null,
    "last_signal": null,
    "last_skip": null,
    "status": "ok",
    "last_trade_at": null,
    "health_state": "active",
    "why_no_trade": "No trade yet",
    "size_multiplier": null,
    "recent_pnl": 0.0,
    "recent_win_rate": 0
  },
  {
    "engine": "C",
    "label": "Engine C ORB",
    "last_run": null,
    "last_signal": null,
    "last_skip": null,
    "status": "ok",
    "last_trade_at": null,
    "health_state": "active",
    "why_no_trade": "No trade yet",
    "size_multiplier": null,
    "recent_pnl": 0.0,
    "recent_win_rate": 0
  },
  {
    "engine": "D",
    "label": "Engine D Scanner",
    "last_run": null,
    "last_signal": null,
    "last_skip": null,
    "status": "ok",
    "last_trade_at": null,
    "health_state": "active",
    "why_no_trade": "No trade yet",
    "size_multiplier": null,
    "recent_pnl": 0.0,
    "recent_win_rate": 0
  },
  {
    "engine": "crypto_24_7",
    "label": "Crypto 24/7",
    "last_run": null,
    "last_signal": null,
    "last_skip": null,
    "status": "ok",
    "last_trade_at": null,
    "health_state": "active",
    "why_no_trade": "No trade yet",
    "size_multiplier": null,
    "recent_pnl": 0.0,
    "recent_win_rate": 0
  },
  {
    "engine": "crypto_john",
    "label": "Crypto John Live",
    "last_run": null,
    "last_signal": null,
    "last_skip": null,
    "status": "ok",
    "last_trade_at": null,
    "health_state": "active",
    "why_no_trade": "No trade yet",
    "size_multiplier": null,
    "recent_pnl": 0.0,
    "recent_win_rate": 0
  },
  {
    "engine": "xau_grid",
    "label": "XAU Grid",
    "last_run": null,
    "last_signal": null,
    "last_skip": null,
    "status": "ok",
    "last_trade_at": null,
    "health_state": "active",
    "why_no_trade": "No trade yet",
    "size_multiplier": null,
    "recent_pnl": 0.0,
    "recent_win_rate": 0
  }
]