[
  {
    "symbol": "COPX",
    "engine": "unknown",
    "status": "WATCHLIST",
    "score": 18,
    "bull_case": "Entry valid while price respects setup and stop.",
    "bear_case": "Invalidates if stop/kill level breaks or crypto exposure spikes.",
    "kill_criteria": "Stop 82.64",
    "rr": null,
    "risk_dollars": 23.58
  },
  {
    "symbol": "QQQ",
    "engine": "unknown",
    "status": "WATCHLIST",
    "score": 18,
    "bull_case": "Entry valid while price respects setup and stop.",
    "bear_case": "Invalidates if stop/kill level breaks or crypto exposure spikes.",
    "kill_criteria": "Stop 672.62",
    "rr": null,
    "risk_dollars": 20.17
  },
  {
    "symbol": "AMZN",
    "engine": "unknown",
    "status": "WATCHLIST",
    "score": 18,
    "bull_case": "Entry valid while price respects setup and stop.",
    "bear_case": "Invalidates if stop/kill level breaks or crypto exposure spikes.",
    "kill_criteria": "Stop 265.14",
    "rr": null,
    "risk_dollars": 15.9
  },
  {
    "symbol": "NFLX",
    "engine": "unknown",
    "status": "WATCHLIST",
    "score": 18,
    "bull_case": "Entry valid while price respects setup and stop.",
    "bear_case": "Invalidates if stop/kill level breaks or crypto exposure spikes.",
    "kill_criteria": "Stop 93.65",
    "rr": null,
    "risk_dollars": 27.6
  },
  {
    "symbol": "GOOG",
    "engine": "unknown",
    "status": "WATCHLIST",
    "score": 18,
    "bull_case": "Entry valid while price respects setup and stop.",
    "bear_case": "Invalidates if stop/kill level breaks or crypto exposure spikes.",
    "kill_criteria": "Stop 341.85",
    "rr": null,
    "risk_dollars": 18.83
  }
]